SimpleSLACalc/__init__.py
SimpleSLACalc/exceptions.py
SimpleSLACalc/sla_calc.py
simpleslacalc-0.0.63.dist-info/METADATA
simpleslacalc-0.0.63.dist-info/WHEEL
simpleslacalc-0.0.63.dist-info/top_level.txt
simpleslacalc-0.0.63.dist-info/RECORD
